inversql/__init__.py
inversql/errors.py
inversql/highlights/__init__.py
inversql/highlights/cells.py
inversql/highlights/headers.py
inversql/highlights/highlights.py
inversql/ui/app.py
inversql/ui/controller.py
inversql/ui/data_model.py
inversql/ui/multi_csv_viewer.tcss
inversql/ui/widgets.py
inversql-0.0.1.dist-info/METADATA
inversql-0.0.1.dist-info/WHEEL
inversql-0.0.1.dist-info/top_level.txt
inversql-0.0.1.dist-info/RECORD
